quest_qso/__init__.py
quest_qso/mlconfig.py
quest_qso/error_function/compute.py
quest_qso/error_function/qa_plots.py
quest_qso/examples/generate_photometry_sdss.ipynb
quest_qso/models/__init__.py
quest_qso/models/cvae.py
quest_qso/models/info_vae.py
quest_qso/models/nflow.py
quest_qso/models/vae.py
quest_qso/photometry/custom_filters.py
quest_qso/photometry/generate_photometry.py
quest_qso/photometry/igm_simqso.py
quest_qso/photometry/qa_plots.py
quest_qso/plots/paper_plots.ipynb
quest_qso/plots/qa_plots.py
quest_qso/plots/qa_plots_paper.py
quest_qso/plots/tol_colors.py
quest_qso/scripts/add_pert.py
quest_qso/scripts/generate_photometry.py
quest_qso/scripts/latent_space.py
quest_qso/scripts/plot_training_results.py
quest_qso/scripts/train_composite_infovae.py
quest_qso/utils/deredden.py
quest_qso/utils/early_stopping.py
quest_qso/utils/generate_photometry_utils.py
quest_qso/utils/load.py
quest_qso/utils/resources.py
quest_qso/utils/spec_dataset.py
quest_qso/utils/train_utils.py
quest_qso/utils/utilities.py
quest_qso-1.0.1.dist-info/METADATA
quest_qso-1.0.1.dist-info/WHEEL
quest_qso-1.0.1.dist-info/licenses/LICENSE
quest_qso-1.0.1.dist-info/RECORD
