Metadata-Version: 2.4
Name: quest_qso
Version: 1.0.1
Summary: A machine learning model to generate quasar spectra
Project-URL: Homepage, https://github.com/cosmic-dawn-group/QUEST
Project-URL: Bug Tracker, https://github.com/cosmic-dawn-group/QUEST/issues
Author-email: Francesco Guarneri <francesco.guarneri@uni-hamburg.de>, Jan-Torge Schindler <jan-torge.schindler@uni-hamburg.de>
License: BSD 3-Clause License
License-File: LICENSE
Keywords: astronomy,python,quasar,science,spectroscopy
Classifier: Development Status :: 4 - Beta
Classifier: Intended Audience :: Science/Research
Classifier: License :: OSI Approved :: BSD License
Classifier: Operating System :: OS Independent
Classifier: Programming Language :: Python :: 3.12
Classifier: Topic :: Scientific/Engineering :: Astronomy
Classifier: Topic :: Scientific/Engineering :: Physics
Requires-Python: <3.13,>=3.12
Requires-Dist: astropy>=6.1.6
Requires-Dist: atelier>=0.1
Requires-Dist: corner>=2.2.3
Requires-Dist: csaps>=1.2.0
Requires-Dist: cuda-selector>=0.1.5
Requires-Dist: dustmaps>=1.0.13
Requires-Dist: emcee>=3.1.6
Requires-Dist: gdown>=5.2.0
Requires-Dist: gmm-mi>=0.8.2
Requires-Dist: h5py>=3.12.1
Requires-Dist: jupyterlab>=4.3.0
Requires-Dist: matplotlib>=3.9.2
Requires-Dist: numba-extinction>=0.1.2
Requires-Dist: numba>=0.60.0
Requires-Dist: numpy>=2.0.2
Requires-Dist: pandas>=2.2.3
Requires-Dist: scikit-learn>=1.5.2
Requires-Dist: scipy>=1.14.1
Requires-Dist: speclite>=0.20
Requires-Dist: spectres>=2.2.2
Requires-Dist: tables>=3.10.1
Requires-Dist: torch>=2.5.1
Requires-Dist: torchvision>=0.20.1
Requires-Dist: tqdm>=4.67.0
Requires-Dist: umap-learn>=0.5.7
